pineDOS
