Metadata-Version: 2.1
Name: pineDOS
Version: 0.0.4
Summary: This library is created to write mini-programms for Pineapple-IV (Imitation of DOS systems)
Author: yaroslav_k
Keywords: files pineapple customisible_text custom
Classifier: License :: OSI Approved :: MIT License
Classifier: Operating System :: OS Independent
